odoo/addons/product_warranty/README.rst
odoo/addons/product_warranty/__init__.py
odoo/addons/product_warranty/__manifest__.py
odoo/addons/product_warranty/demo/product_warranty.xml
odoo/addons/product_warranty/demo/res_company.xml
odoo/addons/product_warranty/i18n/es.po
odoo/addons/product_warranty/i18n/es_MX.po
odoo/addons/product_warranty/i18n/es_PA.po
odoo/addons/product_warranty/i18n/es_VE.po
odoo/addons/product_warranty/i18n/fr.po
odoo/addons/product_warranty/i18n/product_warranty.pot
odoo/addons/product_warranty/i18n/pt.po
odoo/addons/product_warranty/i18n/pt_BR.po
odoo/addons/product_warranty/images/product_warranty.png
odoo/addons/product_warranty/models/__init__.py
odoo/addons/product_warranty/models/product_supplierinfo.py
odoo/addons/product_warranty/models/product_template.py
odoo/addons/product_warranty/models/res_company.py
odoo/addons/product_warranty/models/return_instruction.py
odoo/addons/product_warranty/readme/CONTRIBUTORS.rst
odoo/addons/product_warranty/readme/CREDITS.rst
odoo/addons/product_warranty/readme/DESCRIPTION.rst
odoo/addons/product_warranty/readme/USAGE.rst
odoo/addons/product_warranty/security/ir.model.access.csv
odoo/addons/product_warranty/static/description/icon.png
odoo/addons/product_warranty/static/description/index.html
odoo/addons/product_warranty/tests/__init__.py
odoo/addons/product_warranty/tests/test_product_warranty.py
odoo/addons/product_warranty/views/product_template.xml
odoo/addons/product_warranty/views/product_warranty.xml
odoo/addons/product_warranty/views/res_company.xml
odoo12_addon_product_warranty-12.0.1.0.0.99.dev11.dist-info/METADATA
odoo12_addon_product_warranty-12.0.1.0.0.99.dev11.dist-info/WHEEL
odoo12_addon_product_warranty-12.0.1.0.0.99.dev11.dist-info/top_level.txt
odoo12_addon_product_warranty-12.0.1.0.0.99.dev11.dist-info/RECORD
